picslate/__init__.py
picslate/__main__.py
picslate/core.py
picslate/corrector.py
picslate/make_picture.py
picslate/paragraphs.py
picslate/translate.py
picslate/font/map.json
picslate/font/arabic/NotoSansArabic-Regular.ttf
picslate/font/bengali/NotoSansBengali-Regular.ttf
picslate/font/canadian_arbo/NotoSansCanadianAboriginal-Regular.ttf
picslate/font/cherokee/NotoSansCherokee-Regular.ttf
picslate/font/chinese_sim/NotoSansSC-Regular.otf
picslate/font/chinese_trad/NotoSansTC-Regular.otf
picslate/font/cypriot/NotoSansCypriot-Regular.ttf
picslate/font/devanagari/NotoSansDevanagari-Regular.ttf
picslate/font/ethiopic/NotoSansEthiopic-Regular.ttf
picslate/font/georgian/NotoSansGeorgian-Regular.ttf
picslate/font/gujarati/NotoSansGujarati-Regular.ttf
picslate/font/gurmukhi/NotoSansGurmukhi-Regular.ttf
picslate/font/hebrew/NotoSansHebrew-Regular.ttf
picslate/font/japanese/NotoSansJP-Regular.otf
picslate/font/kannada/NotoSansKannada-Regular.ttf
picslate/font/khmer/NotoSansKhmer-Regular.ttf
picslate/font/korean/NotoSansKR-Regular.otf
picslate/font/lao/NotoSansLao-Regular.ttf
picslate/font/latin/NotoSans-Regular.ttf
picslate/font/malayalam/NotoSansMalayalam-Regular.ttf
picslate/font/myanmar/NotoSansMyanmar-Regular.ttf
picslate/font/oriya/NotoSansOriya-Regular.ttf
picslate/font/sinhala/NotoSansSinhala-Regular.ttf
picslate/font/syriac/NotoSansSyriac-Regular.ttf
picslate/font/tagalog/NotoSansTagalog-Regular.ttf
picslate/font/tamil/NotoSansTamil-Regular.ttf
picslate/font/telugu/NotoSansTelugu-Regular.ttf
picslate/font/thai/NotoSansThai-Regular.ttf
picslate/font/tibetan/NotoSerifTibetan-Regular.ttf
picslate/tesseract/lang.json
picslate/tesseract/picture.py
picslate-0.3.1.dist-info/LICENSE.md
picslate-0.3.1.dist-info/METADATA
picslate-0.3.1.dist-info/WHEEL
picslate-0.3.1.dist-info/entry_points.txt
picslate-0.3.1.dist-info/top_level.txt
picslate-0.3.1.dist-info/RECORD
