Metadata-Version: 2.1
Name: picslate
Version: 0.3.1
Summary: Picture ocr & translation
Author: Thomas Portier
License-File: LICENSE.md
Requires-Dist: numpy (>=1.19.4)
Requires-Dist: tesserocr
